apigateway/__init__.py
apigateway/cli.py
llm_apigateway-0.1.1.dist-info/LICENSE
llm_apigateway-0.1.1.dist-info/METADATA
llm_apigateway-0.1.1.dist-info/WHEEL
llm_apigateway-0.1.1.dist-info/entry_points.txt
llm_apigateway-0.1.1.dist-info/top_level.txt
llm_apigateway-0.1.1.dist-info/RECORD
